[
	{
		"Name":"Hidden",
		"RenderTargetRequired":false,
		"RenderTargetFieldOfView":5,
		"RenderTargetTexture":"None",
		"RenderMaterialSlotName":"Render",
		"RenderMaterialReplacement":"None",
		"OffsetStanding":
		{
			"Rotation":
			{
				"X":0,
				"Y":0,
				"Z":0,
				"W":1
			},
			"Translation":
			{
				"X":0,
				"Y":0,
				"Z":0
			},
			"Scale3D":
			{
				"X":1,
				"Y":1,
				"Z":1
			}
		},
		"OffsetAiming":
		{
			"Rotation":
			{
				"X":0,
				"Y":0,
				"Z":0,
				"W":1
			},
			"Translation":
			{
				"X":0,
				"Y":0,
				"Z":0
			},
			"Scale3D":
			{
				"X":1,
				"Y":1,
				"Z":1
			}
		},
		"MultiplierLagValues":
		{
			"Movement":
			{
				"Location":
				{
					"Horizontal":
					{
						"X":1,
						"Y":1,
						"Z":1
					},
					"Vertical":
					{
						"X":1,
						"Y":1,
						"Z":1
					}
				},
				"Rotation":
				{
					"Horizontal":
					{
						"X":1,
						"Y":1,
						"Z":1
					},
					"Vertical":
					{
						"X":1,
						"Y":1,
						"Z":1
					}
				}
			},
			"Look":
			{
				"Location":
				{
					"Horizontal":
					{
						"X":1,
						"Y":1,
						"Z":1
					},
					"Vertical":
					{
						"X":1,
						"Y":1,
						"Z":1
					}
				},
				"Rotation":
				{
					"Horizontal":
					{
						"X":1,
						"Y":1,
						"Z":1
					},
					"Vertical":
					{
						"X":1,
						"Y":1,
						"Z":1
					}
				}
			},
			"SpringInterpolation":
			{
				"Stiffness":0.40000000596046448,
				"CriticalDampingFactor":0.5,
				"Mass":0.0060000000521540642
			}
		},
		"MultiplierFieldOfView":1,
		"MultiplierAimingSpeed":1,
		"MultiplierSensitivityYaw":1,
		"MultiplierSensitivityPitch":1,
		"RenderMaterial":"None",
		"AimedFieldOfViewViewmodel":90
	},
	{
		"Name":"Assault-Rifle-01",
		"RenderTargetRequired":false,
		"RenderTargetFieldOfView":5,
		"RenderTargetTexture":"None",
		"RenderMaterialSlotName":"Render",
		"RenderMaterialReplacement":"None",
		"OffsetStanding":
		{
			"Rotation":
			{
				"X":0,
				"Y":0,
				"Z":0,
				"W":1
			},
			"Translation":
			{
				"X":0,
				"Y":0,
				"Z":0
			},
			"Scale3D":
			{
				"X":1,
				"Y":1,
				"Z":1
			}
		},
		"OffsetAiming":
		{
			"Rotation":
			{
				"X":0,
				"Y":0,
				"Z":0,
				"W":1
			},
			"Translation":
			{
				"X":0,
				"Y":-1,
				"Z":0
			},
			"Scale3D":
			{
				"X":1,
				"Y":1,
				"Z":1
			}
		},
		"MultiplierLagValues":
		{
			"Movement":
			{
				"Location":
				{
					"Horizontal":
					{
						"X":1,
						"Y":1,
						"Z":1
					},
					"Vertical":
					{
						"X":1,
						"Y":1,
						"Z":1
					}
				},
				"Rotation":
				{
					"Horizontal":
					{
						"X":1,
						"Y":1,
						"Z":1
					},
					"Vertical":
					{
						"X":1,
						"Y":1,
						"Z":1
					}
				}
			},
			"Look":
			{
				"Location":
				{
					"Horizontal":
					{
						"X":1,
						"Y":1,
						"Z":1
					},
					"Vertical":
					{
						"X":1,
						"Y":1,
						"Z":1
					}
				},
				"Rotation":
				{
					"Horizontal":
					{
						"X":1,
						"Y":1,
						"Z":1
					},
					"Vertical":
					{
						"X":1,
						"Y":1,
						"Z":1
					}
				}
			},
			"SpringInterpolation":
			{
				"Stiffness":0.40000000596046448,
				"CriticalDampingFactor":0.5,
				"Mass":0.0060000000521540642
			}
		},
		"MultiplierFieldOfView":0.80000001192092896,
		"MultiplierAimingSpeed":1,
		"MultiplierSensitivityYaw":0.80000001192092896,
		"MultiplierSensitivityPitch":0.80000001192092896,
		"RenderMaterial":"None",
		"AimedFieldOfViewViewmodel":100
	},
	{
		"Name":"Assault-Rifle-02",
		"RenderTargetRequired":false,
		"RenderTargetFieldOfView":5,
		"RenderTargetTexture":"None",
		"RenderMaterialSlotName":"Render",
		"RenderMaterialReplacement":"None",
		"OffsetStanding":
		{
			"Rotation":
			{
				"X":0,
				"Y":0,
				"Z":0,
				"W":1
			},
			"Translation":
			{
				"X":0,
				"Y":0,
				"Z":0
			},
			"Scale3D":
			{
				"X":1,
				"Y":1,
				"Z":1
			}
		},
		"OffsetAiming":
		{
			"Rotation":
			{
				"X":0,
				"Y":0,
				"Z":0,
				"W":1
			},
			"Translation":
			{
				"X":0,
				"Y":16,
				"Z":0
			},
			"Scale3D":
			{
				"X":1,
				"Y":1,
				"Z":1
			}
		},
		"MultiplierLagValues":
		{
			"Movement":
			{
				"Location":
				{
					"Horizontal":
					{
						"X":1,
						"Y":1,
						"Z":1
					},
					"Vertical":
					{
						"X":1,
						"Y":1,
						"Z":1
					}
				},
				"Rotation":
				{
					"Horizontal":
					{
						"X":1,
						"Y":1,
						"Z":1
					},
					"Vertical":
					{
						"X":1,
						"Y":1,
						"Z":1
					}
				}
			},
			"Look":
			{
				"Location":
				{
					"Horizontal":
					{
						"X":1,
						"Y":1,
						"Z":1
					},
					"Vertical":
					{
						"X":1,
						"Y":1,
						"Z":1
					}
				},
				"Rotation":
				{
					"Horizontal":
					{
						"X":1,
						"Y":1,
						"Z":1
					},
					"Vertical":
					{
						"X":1,
						"Y":1,
						"Z":1
					}
				}
			},
			"SpringInterpolation":
			{
				"Stiffness":0.40000000596046448,
				"CriticalDampingFactor":0.5,
				"Mass":0.0060000000521540642
			}
		},
		"MultiplierFieldOfView":0.80000001192092896,
		"MultiplierAimingSpeed":1,
		"MultiplierSensitivityYaw":0.80000001192092896,
		"MultiplierSensitivityPitch":0.80000001192092896,
		"RenderMaterial":"None",
		"AimedFieldOfViewViewmodel":100
	},
	{
		"Name":"Assault-Rifle-03",
		"RenderTargetRequired":false,
		"RenderTargetFieldOfView":5,
		"RenderTargetTexture":"None",
		"RenderMaterialSlotName":"Render",
		"RenderMaterialReplacement":"None",
		"OffsetStanding":
		{
			"Rotation":
			{
				"X":0,
				"Y":0,
				"Z":0,
				"W":1
			},
			"Translation":
			{
				"X":0,
				"Y":0,
				"Z":0
			},
			"Scale3D":
			{
				"X":1,
				"Y":1,
				"Z":1
			}
		},
		"OffsetAiming":
		{
			"Rotation":
			{
				"X":0,
				"Y":0,
				"Z":0,
				"W":1
			},
			"Translation":
			{
				"X":0,
				"Y":18,
				"Z":0
			},
			"Scale3D":
			{
				"X":1,
				"Y":1,
				"Z":1
			}
		},
		"MultiplierLagValues":
		{
			"Movement":
			{
				"Location":
				{
					"Horizontal":
					{
						"X":1,
						"Y":1,
						"Z":1
					},
					"Vertical":
					{
						"X":1,
						"Y":1,
						"Z":1
					}
				},
				"Rotation":
				{
					"Horizontal":
					{
						"X":1,
						"Y":1,
						"Z":1
					},
					"Vertical":
					{
						"X":1,
						"Y":1,
						"Z":1
					}
				}
			},
			"Look":
			{
				"Location":
				{
					"Horizontal":
					{
						"X":1,
						"Y":1,
						"Z":1
					},
					"Vertical":
					{
						"X":1,
						"Y":1,
						"Z":1
					}
				},
				"Rotation":
				{
					"Horizontal":
					{
						"X":1,
						"Y":1,
						"Z":1
					},
					"Vertical":
					{
						"X":1,
						"Y":1,
						"Z":1
					}
				}
			},
			"SpringInterpolation":
			{
				"Stiffness":0.40000000596046448,
				"CriticalDampingFactor":0.5,
				"Mass":0.0060000000521540642
			}
		},
		"MultiplierFieldOfView":0.80000001192092896,
		"MultiplierAimingSpeed":1,
		"MultiplierSensitivityYaw":0.80000001192092896,
		"MultiplierSensitivityPitch":0.80000001192092896,
		"RenderMaterial":"None",
		"AimedFieldOfViewViewmodel":100
	},
	{
		"Name":"Handgun-01",
		"RenderTargetRequired":false,
		"RenderTargetFieldOfView":0,
		"RenderTargetTexture":"None",
		"RenderMaterialSlotName":"None",
		"RenderMaterialReplacement":"None",
		"OffsetStanding":
		{
			"Rotation":
			{
				"X":0,
				"Y":0,
				"Z":0,
				"W":1
			},
			"Translation":
			{
				"X":0,
				"Y":0,
				"Z":0
			},
			"Scale3D":
			{
				"X":1,
				"Y":1,
				"Z":1
			}
		},
		"OffsetAiming":
		{
			"Rotation":
			{
				"X":0,
				"Y":0,
				"Z":0,
				"W":1
			},
			"Translation":
			{
				"X":0,
				"Y":32,
				"Z":0
			},
			"Scale3D":
			{
				"X":1,
				"Y":1,
				"Z":1
			}
		},
		"MultiplierLagValues":
		{
			"Movement":
			{
				"Location":
				{
					"Horizontal":
					{
						"X":1,
						"Y":1,
						"Z":1
					},
					"Vertical":
					{
						"X":1,
						"Y":1,
						"Z":1
					}
				},
				"Rotation":
				{
					"Horizontal":
					{
						"X":1,
						"Y":1,
						"Z":1
					},
					"Vertical":
					{
						"X":1,
						"Y":1,
						"Z":1
					}
				}
			},
			"Look":
			{
				"Location":
				{
					"Horizontal":
					{
						"X":1,
						"Y":1,
						"Z":1
					},
					"Vertical":
					{
						"X":1,
						"Y":1,
						"Z":1
					}
				},
				"Rotation":
				{
					"Horizontal":
					{
						"X":1,
						"Y":1,
						"Z":1
					},
					"Vertical":
					{
						"X":1,
						"Y":1,
						"Z":1
					}
				}
			},
			"SpringInterpolation":
			{
				"Stiffness":0.40000000596046448,
				"CriticalDampingFactor":0.5,
				"Mass":0.0060000000521540642
			}
		},
		"MultiplierFieldOfView":0.80000001192092896,
		"MultiplierAimingSpeed":1,
		"MultiplierSensitivityYaw":0.80000001192092896,
		"MultiplierSensitivityPitch":0.80000001192092896,
		"RenderMaterial":"None",
		"AimedFieldOfViewViewmodel":100
	},
	{
		"Name":"Handgun-02",
		"RenderTargetRequired":false,
		"RenderTargetFieldOfView":0,
		"RenderTargetTexture":"None",
		"RenderMaterialSlotName":"None",
		"RenderMaterialReplacement":"None",
		"OffsetStanding":
		{
			"Rotation":
			{
				"X":0,
				"Y":0,
				"Z":0,
				"W":1
			},
			"Translation":
			{
				"X":0,
				"Y":0,
				"Z":0
			},
			"Scale3D":
			{
				"X":1,
				"Y":1,
				"Z":1
			}
		},
		"OffsetAiming":
		{
			"Rotation":
			{
				"X":0,
				"Y":0,
				"Z":0,
				"W":1
			},
			"Translation":
			{
				"X":0,
				"Y":32,
				"Z":0
			},
			"Scale3D":
			{
				"X":1,
				"Y":1,
				"Z":1
			}
		},
		"MultiplierLagValues":
		{
			"Movement":
			{
				"Location":
				{
					"Horizontal":
					{
						"X":1,
						"Y":1,
						"Z":1
					},
					"Vertical":
					{
						"X":1,
						"Y":1,
						"Z":1
					}
				},
				"Rotation":
				{
					"Horizontal":
					{
						"X":1,
						"Y":1,
						"Z":1
					},
					"Vertical":
					{
						"X":1,
						"Y":1,
						"Z":1
					}
				}
			},
			"Look":
			{
				"Location":
				{
					"Horizontal":
					{
						"X":1,
						"Y":1,
						"Z":1
					},
					"Vertical":
					{
						"X":1,
						"Y":1,
						"Z":1
					}
				},
				"Rotation":
				{
					"Horizontal":
					{
						"X":1,
						"Y":1,
						"Z":1
					},
					"Vertical":
					{
						"X":1,
						"Y":1,
						"Z":1
					}
				}
			},
			"SpringInterpolation":
			{
				"Stiffness":0.40000000596046448,
				"CriticalDampingFactor":0.5,
				"Mass":0.0060000000521540642
			}
		},
		"MultiplierFieldOfView":0.80000001192092896,
		"MultiplierAimingSpeed":1,
		"MultiplierSensitivityYaw":0.80000001192092896,
		"MultiplierSensitivityPitch":0.80000001192092896,
		"RenderMaterial":"None",
		"AimedFieldOfViewViewmodel":100
	},
	{
		"Name":"Handgun-03",
		"RenderTargetRequired":false,
		"RenderTargetFieldOfView":0,
		"RenderTargetTexture":"None",
		"RenderMaterialSlotName":"None",
		"RenderMaterialReplacement":"None",
		"OffsetStanding":
		{
			"Rotation":
			{
				"X":0,
				"Y":0,
				"Z":0,
				"W":1
			},
			"Translation":
			{
				"X":0,
				"Y":0,
				"Z":0
			},
			"Scale3D":
			{
				"X":1,
				"Y":1,
				"Z":1
			}
		},
		"OffsetAiming":
		{
			"Rotation":
			{
				"X":0,
				"Y":0,
				"Z":0,
				"W":1
			},
			"Translation":
			{
				"X":0,
				"Y":32,
				"Z":0
			},
			"Scale3D":
			{
				"X":1,
				"Y":1,
				"Z":1
			}
		},
		"MultiplierLagValues":
		{
			"Movement":
			{
				"Location":
				{
					"Horizontal":
					{
						"X":1,
						"Y":1,
						"Z":1
					},
					"Vertical":
					{
						"X":1,
						"Y":1,
						"Z":1
					}
				},
				"Rotation":
				{
					"Horizontal":
					{
						"X":1,
						"Y":1,
						"Z":1
					},
					"Vertical":
					{
						"X":1,
						"Y":1,
						"Z":1
					}
				}
			},
			"Look":
			{
				"Location":
				{
					"Horizontal":
					{
						"X":1,
						"Y":1,
						"Z":1
					},
					"Vertical":
					{
						"X":1,
						"Y":1,
						"Z":1
					}
				},
				"Rotation":
				{
					"Horizontal":
					{
						"X":1,
						"Y":1,
						"Z":1
					},
					"Vertical":
					{
						"X":1,
						"Y":1,
						"Z":1
					}
				}
			},
			"SpringInterpolation":
			{
				"Stiffness":0.40000000596046448,
				"CriticalDampingFactor":0.5,
				"Mass":0.0060000000521540642
			}
		},
		"MultiplierFieldOfView":0.80000001192092896,
		"MultiplierAimingSpeed":1,
		"MultiplierSensitivityYaw":0.80000001192092896,
		"MultiplierSensitivityPitch":0.80000001192092896,
		"RenderMaterial":"None",
		"AimedFieldOfViewViewmodel":100
	},
	{
		"Name":"Handgun-04",
		"RenderTargetRequired":false,
		"RenderTargetFieldOfView":0,
		"RenderTargetTexture":"None",
		"RenderMaterialSlotName":"None",
		"RenderMaterialReplacement":"None",
		"OffsetStanding":
		{
			"Rotation":
			{
				"X":0,
				"Y":0,
				"Z":0,
				"W":1
			},
			"Translation":
			{
				"X":0,
				"Y":0,
				"Z":0
			},
			"Scale3D":
			{
				"X":1,
				"Y":1,
				"Z":1
			}
		},
		"OffsetAiming":
		{
			"Rotation":
			{
				"X":0,
				"Y":0,
				"Z":0,
				"W":1
			},
			"Translation":
			{
				"X":0,
				"Y":32,
				"Z":0
			},
			"Scale3D":
			{
				"X":1,
				"Y":1,
				"Z":1
			}
		},
		"MultiplierLagValues":
		{
			"Movement":
			{
				"Location":
				{
					"Horizontal":
					{
						"X":1,
						"Y":1,
						"Z":1
					},
					"Vertical":
					{
						"X":1,
						"Y":1,
						"Z":1
					}
				},
				"Rotation":
				{
					"Horizontal":
					{
						"X":1,
						"Y":1,
						"Z":1
					},
					"Vertical":
					{
						"X":1,
						"Y":1,
						"Z":1
					}
				}
			},
			"Look":
			{
				"Location":
				{
					"Horizontal":
					{
						"X":1,
						"Y":1,
						"Z":1
					},
					"Vertical":
					{
						"X":1,
						"Y":1,
						"Z":1
					}
				},
				"Rotation":
				{
					"Horizontal":
					{
						"X":1,
						"Y":1,
						"Z":1
					},
					"Vertical":
					{
						"X":1,
						"Y":1,
						"Z":1
					}
				}
			},
			"SpringInterpolation":
			{
				"Stiffness":0.40000000596046448,
				"CriticalDampingFactor":0.5,
				"Mass":0.0060000000521540642
			}
		},
		"MultiplierFieldOfView":0.80000001192092896,
		"MultiplierAimingSpeed":1,
		"MultiplierSensitivityYaw":0.80000001192092896,
		"MultiplierSensitivityPitch":0.80000001192092896,
		"RenderMaterial":"None",
		"AimedFieldOfViewViewmodel":100
	},
	{
		"Name":"Launcher-Rocket-01",
		"RenderTargetRequired":false,
		"RenderTargetFieldOfView":0,
		"RenderTargetTexture":"None",
		"RenderMaterialSlotName":"None",
		"RenderMaterialReplacement":"None",
		"OffsetStanding":
		{
			"Rotation":
			{
				"X":0,
				"Y":0,
				"Z":0,
				"W":1
			},
			"Translation":
			{
				"X":0,
				"Y":0,
				"Z":0
			},
			"Scale3D":
			{
				"X":1,
				"Y":1,
				"Z":1
			}
		},
		"OffsetAiming":
		{
			"Rotation":
			{
				"X":0,
				"Y":0,
				"Z":0,
				"W":1
			},
			"Translation":
			{
				"X":0,
				"Y":0,
				"Z":0
			},
			"Scale3D":
			{
				"X":1,
				"Y":1,
				"Z":1
			}
		},
		"MultiplierLagValues":
		{
			"Movement":
			{
				"Location":
				{
					"Horizontal":
					{
						"X":1,
						"Y":1,
						"Z":1
					},
					"Vertical":
					{
						"X":1,
						"Y":1,
						"Z":1
					}
				},
				"Rotation":
				{
					"Horizontal":
					{
						"X":1,
						"Y":1,
						"Z":1
					},
					"Vertical":
					{
						"X":1,
						"Y":1,
						"Z":1
					}
				}
			},
			"Look":
			{
				"Location":
				{
					"Horizontal":
					{
						"X":1,
						"Y":1,
						"Z":1
					},
					"Vertical":
					{
						"X":1,
						"Y":1,
						"Z":1
					}
				},
				"Rotation":
				{
					"Horizontal":
					{
						"X":1,
						"Y":1,
						"Z":1
					},
					"Vertical":
					{
						"X":1,
						"Y":1,
						"Z":1
					}
				}
			},
			"SpringInterpolation":
			{
				"Stiffness":0.40000000596046448,
				"CriticalDampingFactor":0.5,
				"Mass":0.0060000000521540642
			}
		},
		"MultiplierFieldOfView":0.80000001192092896,
		"MultiplierAimingSpeed":1,
		"MultiplierSensitivityYaw":0.80000001192092896,
		"MultiplierSensitivityPitch":0.80000001192092896,
		"RenderMaterial":"None",
		"AimedFieldOfViewViewmodel":100
	},
	{
		"Name":"Launcher-Grenade-01",
		"RenderTargetRequired":false,
		"RenderTargetFieldOfView":0,
		"RenderTargetTexture":"None",
		"RenderMaterialSlotName":"None",
		"RenderMaterialReplacement":"None",
		"OffsetStanding":
		{
			"Rotation":
			{
				"X":0,
				"Y":0,
				"Z":0,
				"W":1
			},
			"Translation":
			{
				"X":0,
				"Y":0,
				"Z":0
			},
			"Scale3D":
			{
				"X":1,
				"Y":1,
				"Z":1
			}
		},
		"OffsetAiming":
		{
			"Rotation":
			{
				"X":0,
				"Y":0,
				"Z":0,
				"W":1
			},
			"Translation":
			{
				"X":0,
				"Y":0,
				"Z":0
			},
			"Scale3D":
			{
				"X":1,
				"Y":1,
				"Z":1
			}
		},
		"MultiplierLagValues":
		{
			"Movement":
			{
				"Location":
				{
					"Horizontal":
					{
						"X":1,
						"Y":1,
						"Z":1
					},
					"Vertical":
					{
						"X":1,
						"Y":1,
						"Z":1
					}
				},
				"Rotation":
				{
					"Horizontal":
					{
						"X":1,
						"Y":1,
						"Z":1
					},
					"Vertical":
					{
						"X":1,
						"Y":1,
						"Z":1
					}
				}
			},
			"Look":
			{
				"Location":
				{
					"Horizontal":
					{
						"X":1,
						"Y":1,
						"Z":1
					},
					"Vertical":
					{
						"X":1,
						"Y":1,
						"Z":1
					}
				},
				"Rotation":
				{
					"Horizontal":
					{
						"X":1,
						"Y":1,
						"Z":1
					},
					"Vertical":
					{
						"X":1,
						"Y":1,
						"Z":1
					}
				}
			},
			"SpringInterpolation":
			{
				"Stiffness":0.40000000596046448,
				"CriticalDampingFactor":0.5,
				"Mass":0.0060000000521540642
			}
		},
		"MultiplierFieldOfView":0.80000001192092896,
		"MultiplierAimingSpeed":1,
		"MultiplierSensitivityYaw":0.80000001192092896,
		"MultiplierSensitivityPitch":0.80000001192092896,
		"RenderMaterial":"None",
		"AimedFieldOfViewViewmodel":100
	},
	{
		"Name":"Shotgun-01",
		"RenderTargetRequired":false,
		"RenderTargetFieldOfView":5,
		"RenderTargetTexture":"None",
		"RenderMaterialSlotName":"Render",
		"RenderMaterialReplacement":"None",
		"OffsetStanding":
		{
			"Rotation":
			{
				"X":0,
				"Y":0,
				"Z":0,
				"W":1
			},
			"Translation":
			{
				"X":0,
				"Y":0,
				"Z":0
			},
			"Scale3D":
			{
				"X":1,
				"Y":1,
				"Z":1
			}
		},
		"OffsetAiming":
		{
			"Rotation":
			{
				"X":0,
				"Y":0,
				"Z":0,
				"W":1
			},
			"Translation":
			{
				"X":0,
				"Y":5,
				"Z":0
			},
			"Scale3D":
			{
				"X":1,
				"Y":1,
				"Z":1
			}
		},
		"MultiplierLagValues":
		{
			"Movement":
			{
				"Location":
				{
					"Horizontal":
					{
						"X":1,
						"Y":1,
						"Z":1
					},
					"Vertical":
					{
						"X":1,
						"Y":1,
						"Z":1
					}
				},
				"Rotation":
				{
					"Horizontal":
					{
						"X":1,
						"Y":1,
						"Z":1
					},
					"Vertical":
					{
						"X":1,
						"Y":1,
						"Z":1
					}
				}
			},
			"Look":
			{
				"Location":
				{
					"Horizontal":
					{
						"X":1,
						"Y":1,
						"Z":1
					},
					"Vertical":
					{
						"X":1,
						"Y":1,
						"Z":1
					}
				},
				"Rotation":
				{
					"Horizontal":
					{
						"X":1,
						"Y":1,
						"Z":1
					},
					"Vertical":
					{
						"X":1,
						"Y":1,
						"Z":1
					}
				}
			},
			"SpringInterpolation":
			{
				"Stiffness":0.40000000596046448,
				"CriticalDampingFactor":0.5,
				"Mass":0.0060000000521540642
			}
		},
		"MultiplierFieldOfView":0.80000001192092896,
		"MultiplierAimingSpeed":1,
		"MultiplierSensitivityYaw":0.80000001192092896,
		"MultiplierSensitivityPitch":0.80000001192092896,
		"RenderMaterial":"None",
		"AimedFieldOfViewViewmodel":100
	},
	{
		"Name":"SMG-01",
		"RenderTargetRequired":false,
		"RenderTargetFieldOfView":5,
		"RenderTargetTexture":"None",
		"RenderMaterialSlotName":"Render",
		"RenderMaterialReplacement":"None",
		"OffsetStanding":
		{
			"Rotation":
			{
				"X":0,
				"Y":0,
				"Z":0,
				"W":1
			},
			"Translation":
			{
				"X":0,
				"Y":0,
				"Z":0
			},
			"Scale3D":
			{
				"X":1,
				"Y":1,
				"Z":1
			}
		},
		"OffsetAiming":
		{
			"Rotation":
			{
				"X":0,
				"Y":0,
				"Z":0,
				"W":1
			},
			"Translation":
			{
				"X":0,
				"Y":9,
				"Z":0
			},
			"Scale3D":
			{
				"X":1,
				"Y":1,
				"Z":1
			}
		},
		"MultiplierLagValues":
		{
			"Movement":
			{
				"Location":
				{
					"Horizontal":
					{
						"X":1,
						"Y":1,
						"Z":1
					},
					"Vertical":
					{
						"X":1,
						"Y":1,
						"Z":1
					}
				},
				"Rotation":
				{
					"Horizontal":
					{
						"X":1,
						"Y":1,
						"Z":1
					},
					"Vertical":
					{
						"X":1,
						"Y":1,
						"Z":1
					}
				}
			},
			"Look":
			{
				"Location":
				{
					"Horizontal":
					{
						"X":1,
						"Y":1,
						"Z":1
					},
					"Vertical":
					{
						"X":1,
						"Y":1,
						"Z":1
					}
				},
				"Rotation":
				{
					"Horizontal":
					{
						"X":1,
						"Y":1,
						"Z":1
					},
					"Vertical":
					{
						"X":1,
						"Y":1,
						"Z":1
					}
				}
			},
			"SpringInterpolation":
			{
				"Stiffness":0.40000000596046448,
				"CriticalDampingFactor":0.5,
				"Mass":0.0060000000521540642
			}
		},
		"MultiplierFieldOfView":0.80000001192092896,
		"MultiplierAimingSpeed":1,
		"MultiplierSensitivityYaw":0.80000001192092896,
		"MultiplierSensitivityPitch":0.80000001192092896,
		"RenderMaterial":"None",
		"AimedFieldOfViewViewmodel":100
	},
	{
		"Name":"SMG-02",
		"RenderTargetRequired":false,
		"RenderTargetFieldOfView":5,
		"RenderTargetTexture":"None",
		"RenderMaterialSlotName":"Render",
		"RenderMaterialReplacement":"None",
		"OffsetStanding":
		{
			"Rotation":
			{
				"X":0,
				"Y":0,
				"Z":0,
				"W":1
			},
			"Translation":
			{
				"X":0,
				"Y":0,
				"Z":0
			},
			"Scale3D":
			{
				"X":1,
				"Y":1,
				"Z":1
			}
		},
		"OffsetAiming":
		{
			"Rotation":
			{
				"X":0,
				"Y":0,
				"Z":0,
				"W":1
			},
			"Translation":
			{
				"X":0,
				"Y":17,
				"Z":0
			},
			"Scale3D":
			{
				"X":1,
				"Y":1,
				"Z":1
			}
		},
		"MultiplierLagValues":
		{
			"Movement":
			{
				"Location":
				{
					"Horizontal":
					{
						"X":1,
						"Y":1,
						"Z":1
					},
					"Vertical":
					{
						"X":1,
						"Y":1,
						"Z":1
					}
				},
				"Rotation":
				{
					"Horizontal":
					{
						"X":1,
						"Y":1,
						"Z":1
					},
					"Vertical":
					{
						"X":1,
						"Y":1,
						"Z":1
					}
				}
			},
			"Look":
			{
				"Location":
				{
					"Horizontal":
					{
						"X":1,
						"Y":1,
						"Z":1
					},
					"Vertical":
					{
						"X":1,
						"Y":1,
						"Z":1
					}
				},
				"Rotation":
				{
					"Horizontal":
					{
						"X":1,
						"Y":1,
						"Z":1
					},
					"Vertical":
					{
						"X":1,
						"Y":1,
						"Z":1
					}
				}
			},
			"SpringInterpolation":
			{
				"Stiffness":0.40000000596046448,
				"CriticalDampingFactor":0.5,
				"Mass":0.0060000000521540642
			}
		},
		"MultiplierFieldOfView":0.80000001192092896,
		"MultiplierAimingSpeed":1,
		"MultiplierSensitivityYaw":0.80000001192092896,
		"MultiplierSensitivityPitch":0.80000001192092896,
		"RenderMaterial":"None",
		"AimedFieldOfViewViewmodel":100
	},
	{
		"Name":"SMG-03",
		"RenderTargetRequired":false,
		"RenderTargetFieldOfView":5,
		"RenderTargetTexture":"None",
		"RenderMaterialSlotName":"Render",
		"RenderMaterialReplacement":"None",
		"OffsetStanding":
		{
			"Rotation":
			{
				"X":0,
				"Y":0,
				"Z":0,
				"W":1
			},
			"Translation":
			{
				"X":0,
				"Y":0,
				"Z":0
			},
			"Scale3D":
			{
				"X":1,
				"Y":1,
				"Z":1
			}
		},
		"OffsetAiming":
		{
			"Rotation":
			{
				"X":0,
				"Y":0,
				"Z":0,
				"W":1
			},
			"Translation":
			{
				"X":0,
				"Y":20,
				"Z":0
			},
			"Scale3D":
			{
				"X":1,
				"Y":1,
				"Z":1
			}
		},
		"MultiplierLagValues":
		{
			"Movement":
			{
				"Location":
				{
					"Horizontal":
					{
						"X":1,
						"Y":1,
						"Z":1
					},
					"Vertical":
					{
						"X":1,
						"Y":1,
						"Z":1
					}
				},
				"Rotation":
				{
					"Horizontal":
					{
						"X":1,
						"Y":1,
						"Z":1
					},
					"Vertical":
					{
						"X":1,
						"Y":1,
						"Z":1
					}
				}
			},
			"Look":
			{
				"Location":
				{
					"Horizontal":
					{
						"X":1,
						"Y":1,
						"Z":1
					},
					"Vertical":
					{
						"X":1,
						"Y":1,
						"Z":1
					}
				},
				"Rotation":
				{
					"Horizontal":
					{
						"X":1,
						"Y":1,
						"Z":1
					},
					"Vertical":
					{
						"X":1,
						"Y":1,
						"Z":1
					}
				}
			},
			"SpringInterpolation":
			{
				"Stiffness":0.40000000596046448,
				"CriticalDampingFactor":0.5,
				"Mass":0.0060000000521540642
			}
		},
		"MultiplierFieldOfView":0.80000001192092896,
		"MultiplierAimingSpeed":1,
		"MultiplierSensitivityYaw":0.80000001192092896,
		"MultiplierSensitivityPitch":0.80000001192092896,
		"RenderMaterial":"None",
		"AimedFieldOfViewViewmodel":100
	},
	{
		"Name":"SMG-04",
		"RenderTargetRequired":false,
		"RenderTargetFieldOfView":5,
		"RenderTargetTexture":"None",
		"RenderMaterialSlotName":"Render",
		"RenderMaterialReplacement":"None",
		"OffsetStanding":
		{
			"Rotation":
			{
				"X":0,
				"Y":0,
				"Z":0,
				"W":1
			},
			"Translation":
			{
				"X":0,
				"Y":0,
				"Z":0
			},
			"Scale3D":
			{
				"X":1,
				"Y":1,
				"Z":1
			}
		},
		"OffsetAiming":
		{
			"Rotation":
			{
				"X":0,
				"Y":0,
				"Z":0,
				"W":1
			},
			"Translation":
			{
				"X":0,
				"Y":8,
				"Z":0
			},
			"Scale3D":
			{
				"X":1,
				"Y":1,
				"Z":1
			}
		},
		"MultiplierLagValues":
		{
			"Movement":
			{
				"Location":
				{
					"Horizontal":
					{
						"X":1,
						"Y":1,
						"Z":1
					},
					"Vertical":
					{
						"X":1,
						"Y":1,
						"Z":1
					}
				},
				"Rotation":
				{
					"Horizontal":
					{
						"X":1,
						"Y":1,
						"Z":1
					},
					"Vertical":
					{
						"X":1,
						"Y":1,
						"Z":1
					}
				}
			},
			"Look":
			{
				"Location":
				{
					"Horizontal":
					{
						"X":1,
						"Y":1,
						"Z":1
					},
					"Vertical":
					{
						"X":1,
						"Y":1,
						"Z":1
					}
				},
				"Rotation":
				{
					"Horizontal":
					{
						"X":1,
						"Y":1,
						"Z":1
					},
					"Vertical":
					{
						"X":1,
						"Y":1,
						"Z":1
					}
				}
			},
			"SpringInterpolation":
			{
				"Stiffness":0.40000000596046448,
				"CriticalDampingFactor":0.5,
				"Mass":0.0060000000521540642
			}
		},
		"MultiplierFieldOfView":0.80000001192092896,
		"MultiplierAimingSpeed":1,
		"MultiplierSensitivityYaw":0.80000001192092896,
		"MultiplierSensitivityPitch":0.80000001192092896,
		"RenderMaterial":"None",
		"AimedFieldOfViewViewmodel":100
	},
	{
		"Name":"SMG-05",
		"RenderTargetRequired":false,
		"RenderTargetFieldOfView":5,
		"RenderTargetTexture":"None",
		"RenderMaterialSlotName":"Render",
		"RenderMaterialReplacement":"None",
		"OffsetStanding":
		{
			"Rotation":
			{
				"X":0,
				"Y":0,
				"Z":0,
				"W":1
			},
			"Translation":
			{
				"X":0,
				"Y":0,
				"Z":0
			},
			"Scale3D":
			{
				"X":1,
				"Y":1,
				"Z":1
			}
		},
		"OffsetAiming":
		{
			"Rotation":
			{
				"X":0,
				"Y":0,
				"Z":0,
				"W":1
			},
			"Translation":
			{
				"X":0,
				"Y":10,
				"Z":0
			},
			"Scale3D":
			{
				"X":1,
				"Y":1,
				"Z":1
			}
		},
		"MultiplierLagValues":
		{
			"Movement":
			{
				"Location":
				{
					"Horizontal":
					{
						"X":1,
						"Y":1,
						"Z":1
					},
					"Vertical":
					{
						"X":1,
						"Y":1,
						"Z":1
					}
				},
				"Rotation":
				{
					"Horizontal":
					{
						"X":1,
						"Y":1,
						"Z":1
					},
					"Vertical":
					{
						"X":1,
						"Y":1,
						"Z":1
					}
				}
			},
			"Look":
			{
				"Location":
				{
					"Horizontal":
					{
						"X":1,
						"Y":1,
						"Z":1
					},
					"Vertical":
					{
						"X":1,
						"Y":1,
						"Z":1
					}
				},
				"Rotation":
				{
					"Horizontal":
					{
						"X":1,
						"Y":1,
						"Z":1
					},
					"Vertical":
					{
						"X":1,
						"Y":1,
						"Z":1
					}
				}
			},
			"SpringInterpolation":
			{
				"Stiffness":0.40000000596046448,
				"CriticalDampingFactor":0.5,
				"Mass":0.0060000000521540642
			}
		},
		"MultiplierFieldOfView":0.80000001192092896,
		"MultiplierAimingSpeed":1,
		"MultiplierSensitivityYaw":0.80000001192092896,
		"MultiplierSensitivityPitch":0.80000001192092896,
		"RenderMaterial":"None",
		"AimedFieldOfViewViewmodel":100
	},
	{
		"Name":"Sniper-01",
		"RenderTargetRequired":false,
		"RenderTargetFieldOfView":5,
		"RenderTargetTexture":"None",
		"RenderMaterialSlotName":"Render",
		"RenderMaterialReplacement":"None",
		"OffsetStanding":
		{
			"Rotation":
			{
				"X":0,
				"Y":0,
				"Z":0,
				"W":1
			},
			"Translation":
			{
				"X":0,
				"Y":0,
				"Z":0
			},
			"Scale3D":
			{
				"X":1,
				"Y":1,
				"Z":1
			}
		},
		"OffsetAiming":
		{
			"Rotation":
			{
				"X":0,
				"Y":0,
				"Z":0,
				"W":1
			},
			"Translation":
			{
				"X":0,
				"Y":4,
				"Z":0
			},
			"Scale3D":
			{
				"X":1,
				"Y":1,
				"Z":1
			}
		},
		"MultiplierLagValues":
		{
			"Movement":
			{
				"Location":
				{
					"Horizontal":
					{
						"X":1,
						"Y":1,
						"Z":1
					},
					"Vertical":
					{
						"X":1,
						"Y":1,
						"Z":1
					}
				},
				"Rotation":
				{
					"Horizontal":
					{
						"X":1,
						"Y":1,
						"Z":1
					},
					"Vertical":
					{
						"X":1,
						"Y":1,
						"Z":1
					}
				}
			},
			"Look":
			{
				"Location":
				{
					"Horizontal":
					{
						"X":1,
						"Y":1,
						"Z":1
					},
					"Vertical":
					{
						"X":1,
						"Y":1,
						"Z":1
					}
				},
				"Rotation":
				{
					"Horizontal":
					{
						"X":1,
						"Y":1,
						"Z":1
					},
					"Vertical":
					{
						"X":1,
						"Y":1,
						"Z":1
					}
				}
			},
			"SpringInterpolation":
			{
				"Stiffness":0.40000000596046448,
				"CriticalDampingFactor":0.5,
				"Mass":0.0060000000521540642
			}
		},
		"MultiplierFieldOfView":0.80000001192092896,
		"MultiplierAimingSpeed":1,
		"MultiplierSensitivityYaw":0.80000001192092896,
		"MultiplierSensitivityPitch":0.80000001192092896,
		"RenderMaterial":"None",
		"AimedFieldOfViewViewmodel":100
	},
	{
		"Name":"Sniper-02",
		"RenderTargetRequired":false,
		"RenderTargetFieldOfView":5,
		"RenderTargetTexture":"None",
		"RenderMaterialSlotName":"Render",
		"RenderMaterialReplacement":"None",
		"OffsetStanding":
		{
			"Rotation":
			{
				"X":0,
				"Y":0,
				"Z":0,
				"W":1
			},
			"Translation":
			{
				"X":0,
				"Y":0,
				"Z":0
			},
			"Scale3D":
			{
				"X":1,
				"Y":1,
				"Z":1
			}
		},
		"OffsetAiming":
		{
			"Rotation":
			{
				"X":0,
				"Y":0,
				"Z":0,
				"W":1
			},
			"Translation":
			{
				"X":0,
				"Y":5,
				"Z":0
			},
			"Scale3D":
			{
				"X":1,
				"Y":1,
				"Z":1
			}
		},
		"MultiplierLagValues":
		{
			"Movement":
			{
				"Location":
				{
					"Horizontal":
					{
						"X":1,
						"Y":1,
						"Z":1
					},
					"Vertical":
					{
						"X":1,
						"Y":1,
						"Z":1
					}
				},
				"Rotation":
				{
					"Horizontal":
					{
						"X":1,
						"Y":1,
						"Z":1
					},
					"Vertical":
					{
						"X":1,
						"Y":1,
						"Z":1
					}
				}
			},
			"Look":
			{
				"Location":
				{
					"Horizontal":
					{
						"X":1,
						"Y":1,
						"Z":1
					},
					"Vertical":
					{
						"X":1,
						"Y":1,
						"Z":1
					}
				},
				"Rotation":
				{
					"Horizontal":
					{
						"X":1,
						"Y":1,
						"Z":1
					},
					"Vertical":
					{
						"X":1,
						"Y":1,
						"Z":1
					}
				}
			},
			"SpringInterpolation":
			{
				"Stiffness":0.40000000596046448,
				"CriticalDampingFactor":0.5,
				"Mass":0.0060000000521540642
			}
		},
		"MultiplierFieldOfView":0.80000001192092896,
		"MultiplierAimingSpeed":1,
		"MultiplierSensitivityYaw":0.80000001192092896,
		"MultiplierSensitivityPitch":0.80000001192092896,
		"RenderMaterial":"None",
		"AimedFieldOfViewViewmodel":100
	},
	{
		"Name":"Sniper-03",
		"RenderTargetRequired":false,
		"RenderTargetFieldOfView":5,
		"RenderTargetTexture":"None",
		"RenderMaterialSlotName":"Render",
		"RenderMaterialReplacement":"None",
		"OffsetStanding":
		{
			"Rotation":
			{
				"X":0,
				"Y":0,
				"Z":0,
				"W":1
			},
			"Translation":
			{
				"X":0,
				"Y":0,
				"Z":0
			},
			"Scale3D":
			{
				"X":1,
				"Y":1,
				"Z":1
			}
		},
		"OffsetAiming":
		{
			"Rotation":
			{
				"X":0,
				"Y":0,
				"Z":0,
				"W":1
			},
			"Translation":
			{
				"X":0,
				"Y":8.5,
				"Z":0
			},
			"Scale3D":
			{
				"X":1,
				"Y":1,
				"Z":1
			}
		},
		"MultiplierLagValues":
		{
			"Movement":
			{
				"Location":
				{
					"Horizontal":
					{
						"X":1,
						"Y":1,
						"Z":1
					},
					"Vertical":
					{
						"X":1,
						"Y":1,
						"Z":1
					}
				},
				"Rotation":
				{
					"Horizontal":
					{
						"X":1,
						"Y":1,
						"Z":1
					},
					"Vertical":
					{
						"X":1,
						"Y":1,
						"Z":1
					}
				}
			},
			"Look":
			{
				"Location":
				{
					"Horizontal":
					{
						"X":1,
						"Y":1,
						"Z":1
					},
					"Vertical":
					{
						"X":1,
						"Y":1,
						"Z":1
					}
				},
				"Rotation":
				{
					"Horizontal":
					{
						"X":1,
						"Y":1,
						"Z":1
					},
					"Vertical":
					{
						"X":1,
						"Y":1,
						"Z":1
					}
				}
			},
			"SpringInterpolation":
			{
				"Stiffness":0.40000000596046448,
				"CriticalDampingFactor":0.5,
				"Mass":0.0060000000521540642
			}
		},
		"MultiplierFieldOfView":0.80000001192092896,
		"MultiplierAimingSpeed":1,
		"MultiplierSensitivityYaw":0.80000001192092896,
		"MultiplierSensitivityPitch":0.80000001192092896,
		"RenderMaterial":"None",
		"AimedFieldOfViewViewmodel":100
	}
]